giza_sdk/__init__.py
giza_sdk-0.1.2.dist-info/LICENSE
giza_sdk-0.1.2.dist-info/METADATA
giza_sdk-0.1.2.dist-info/WHEEL
giza_sdk-0.1.2.dist-info/RECORD
