Metadata-Version: 2.1
Name: giza-sdk
Version: 0.1.2
Summary: Metapackage for installing Giza packages
Home-page: https://github.com/gizatechxyz/giza-sdk
License: MIT
Author: Tu Nombre
Author-email: tuemail@example.com
Requires-Python: >=3.11,<4.0
Classifier: License :: OSI Approved :: MIT License
Classifier: Programming Language :: Python :: 3
Classifier: Programming Language :: Python :: 3.11
Classifier: Programming Language :: Python :: 3.12
Requires-Dist: giza-agents (>=0.4.2)
Requires-Dist: giza-cli (>=0.17.0)
Requires-Dist: giza-datasets (>=0.3.0)
Requires-Dist: giza-zkcook (>=0.2.1,<0.3.0)
Project-URL: Repository, https://github.com/gizatechxyz/giza-sdk
